autocommit/__init__.py
autocommit/cli.py
autocommit_cli-0.1.2.dist-info/licenses/LICENSE.md
autocommit_cli-0.1.2.dist-info/METADATA
autocommit_cli-0.1.2.dist-info/WHEEL
autocommit_cli-0.1.2.dist-info/entry_points.txt
autocommit_cli-0.1.2.dist-info/top_level.txt
autocommit_cli-0.1.2.dist-info/RECORD
