Metadata-Version: 2.4
Name: autocommit-cli
Version: 0.1.2
Summary: A CLI tool for AI-powered Git commit messages using Google Gemini API.
Home-page: https://github.com/Pranjal-88/Autocommit-CLI
Author: Pranjal Kishor
License: MIT
Classifier: Programming Language :: Python :: 3
Classifier: License :: OSI Approved :: MIT License
Classifier: Operating System :: OS Independent
Requires-Python: >=3.7
License-File: LICENSE.md
Requires-Dist: click
Requires-Dist: gitpython
Requires-Dist: python-dotenv
Requires-Dist: google-generativeai
Dynamic: author
Dynamic: classifier
Dynamic: description
Dynamic: description-content-type
Dynamic: home-page
Dynamic: license
Dynamic: license-file
Dynamic: requires-dist
Dynamic: requires-python
Dynamic: summary
